README.md
setup.cfg
setup.py
azure_kusto_ingestion_tools.egg-info/PKG-INFO
azure_kusto_ingestion_tools.egg-info/SOURCES.txt
azure_kusto_ingestion_tools.egg-info/dependency_links.txt
azure_kusto_ingestion_tools.egg-info/entry_points.txt
azure_kusto_ingestion_tools.egg-info/requires.txt
azure_kusto_ingestion_tools.egg-info/top_level.txt
kit/__init__.py
kit/cli.py
kit/enums.py
kit/exceptions.py
kit/helpers.py
kit/sql.py
kit/backends/__init__.py
kit/backends/azure_storage.py
kit/backends/fs.py
kit/backends/kusto.py
kit/core/__init__.py
kit/core/ingestion.py
kit/dtypes/__init__.py
kit/dtypes/infer.py
kit/dtypes/resolver.py
kit/models/__init__.py
kit/models/basic.py
kit/models/cdm.py
kit/models/data_source.py
kit/models/database.py
kit/models/ingestion.py
kit/models/mappings.py
kit/models/serializable.py
kit/specifications/__init__.py
kit/specifications/kql.py
kit/specifications/sql.py